nexussdk/__init__.py
nexussdk/hackathon_nexus_sdk.py
nexussdk5-5.1.0.dist-info/LICENSE.txt
nexussdk5-5.1.0.dist-info/METADATA
nexussdk5-5.1.0.dist-info/WHEEL
nexussdk5-5.1.0.dist-info/top_level.txt
nexussdk5-5.1.0.dist-info/RECORD
